decorators/__init__.py
decorators/decorators.py
decorators_pkg/__init__.py
pylioshelpers/__init__.py
pylioshelpers/decorators/__init__.py
pylioshelpers/decorators/decorators.py
pylioshelpers/decorators/test.py
pylioshelpers/logging/__init__.py
pylioshelpers/logging/logging.py
pylioshelpers/logging/test.py
pylioshelpers-0.1.0.dist-info/LICENSE
pylioshelpers-0.1.0.dist-info/METADATA
pylioshelpers-0.1.0.dist-info/WHEEL
pylioshelpers-0.1.0.dist-info/top_level.txt
pylioshelpers-0.1.0.dist-info/RECORD
