Metadata-Version: 2.1
Name: pylioshelpers
Version: 0.1.0
Summary: Set of helpers for Pylios
Home-page: https://github.com/pylios/pylioshelpers
Author: Matt Walters
License: UNKNOWN
Platform: UNKNOWN
Classifier: Programming Language :: Python :: 3
Classifier: License :: OSI Approved :: MIT License
Classifier: Operating System :: OS Independent
Requires-Python: >=3.8
